{"RuleTriggered": 0, "Violations": 0, "Details": {"Network": {"algo-1": {"max": 65162454.6, "p99": 0, "p95": 0, "p50": 0, "min": 0}}, "GPU": {"algo-1": {"max": 0, "p99": 0, "p95": 0, "p50": 0, "min": 0}}, "CPU": {"algo-1": {"max": 86.82, "p99": 72.93, "p95": 63.46, "p50": 55.62, "min": 13.92}}, "CPU memory": {"algo-1": {"max": 5.0, "p99": 4.81, "p95": 4.5, "p50": 3.72, "min": 2.15}}, "GPU memory": {"algo-1": {"max": 0, "p99": 0, "p95": 0, "p50": 0, "min": 0}}, "I/O": {"algo-1": {"max": 45.66, "p99": 29.66, "p95": 15.74, "p50": 0, "min": 0}}}, "Datapoints": 3738, "RuleParameters": ""}